Metadata-Version: 1.0
Name: spycmdbsdkcore
Version: 0.31
Summary: spy cmdb api sdk core
Home-page: https://github.com/feeir
Author: feeir
Author-email: 54587841@qq.com
License: UNKNOWN
Keywords: python english translation dictionary terminal
Platform: UNKNOWN
